types_xmldiff-2.7.0.20251010.dist-info/licenses/LICENSE
xmldiff-stubs/METADATA.toml
xmldiff-stubs/__init__.pyi
xmldiff-stubs/actions.pyi
xmldiff-stubs/diff.pyi
xmldiff-stubs/diff_match_patch.pyi
xmldiff-stubs/formatting.pyi
xmldiff-stubs/main.pyi
xmldiff-stubs/patch.pyi
xmldiff-stubs/py.typed
xmldiff-stubs/utils.pyi
types_xmldiff-2.7.0.20251010.dist-info/METADATA
types_xmldiff-2.7.0.20251010.dist-info/WHEEL
types_xmldiff-2.7.0.20251010.dist-info/top_level.txt
types_xmldiff-2.7.0.20251010.dist-info/RECORD
